mcp_perforce/__init__.py
mcp_perforce/server.py
mcp_perforce-0.3.0.dist-info/METADATA
mcp_perforce-0.3.0.dist-info/WHEEL
mcp_perforce-0.3.0.dist-info/entry_points.txt
mcp_perforce-0.3.0.dist-info/RECORD
