Metadata-Version: 2.4
Name: mcp-perforce
Version: 0.3.0
Summary: MCP server for Perforce code review - supports P4 native commands
Requires-Python: >=3.12
Requires-Dist: mcp>=1.3.0
